mapmatcher4gmns/__init__.py
mapmatcher4gmns/settings.py
mapmatcher4gmns/io/__init__.py
mapmatcher4gmns/io/load_from_csv.py
mapmatcher4gmns/matcher/__init__.py
mapmatcher4gmns/matcher/mapmatch.py
mapmatcher4gmns/networkclass/__init__.py
mapmatcher4gmns/networkclass/basenet.py
mapmatcher4gmns/networkclass/macronet.py
mapmatcher4gmns/utils/__init__.py
mapmatcher4gmns/utils/util_coord.py
mapmatcher4gmns/utils/util_geo.py
mapmatcher4gmns/utils/util_mvmt.py
mapmatcher4gmns-0.1.5.dist-info/licenses/LICENSE
mapmatcher4gmns-0.1.5.dist-info/METADATA
mapmatcher4gmns-0.1.5.dist-info/WHEEL
mapmatcher4gmns-0.1.5.dist-info/top_level.txt
mapmatcher4gmns-0.1.5.dist-info/RECORD
