Metadata-Version: 2.4
Name: mapmatcher4gmns
Version: 0.1.5
Summary: A high-performance map matching tool for GMNS networks
Author-email: Yajun Liu <yajunliu@asu.edu>
License: MIT
Keywords: map-matching,GMNS,GPS,transportation,GIS
Classifier: Development Status :: 3 - Alpha
Classifier: Intended Audience :: Science/Research
Classifier: Intended Audience :: Developers
Classifier: License :: OSI Approved :: MIT License
Classifier: Programming Language :: Python :: 3
Classifier: Programming Language :: Python :: 3.8
Classifier: Programming Language :: Python :: 3.9
Classifier: Programming Language :: Python :: 3.10
Classifier: Programming Language :: Python :: 3.11
Classifier: Programming Language :: Python :: 3.12
Classifier: Topic :: Scientific/Engineering :: GIS
Requires-Python: >=3.8
License-File: LICENSE
Requires-Dist: numpy>=1.20.0
Requires-Dist: pandas>=1.3.0
Requires-Dist: shapely>=2.0.0
Requires-Dist: geopandas>=0.10.0
Requires-Dist: networkx>=2.6.0
Requires-Dist: tqdm>=4.60.0
Dynamic: license-file
